pypkgs_iz/__init__.py
pypkgs_iz/pypkgs_iz.py
pypkgs_iz-0.1.0.dist-info/LICENSE
pypkgs_iz-0.1.0.dist-info/WHEEL
pypkgs_iz-0.1.0.dist-info/METADATA
pypkgs_iz-0.1.0.dist-info/RECORD
