Metadata-Version: 2.1
Name: pypkgs-iz
Version: 0.1.0
Summary: Python package that eases the pain of concatenating Pandas categoricals!
License: MIT
Author: Ivy Zhang
Author-email: ivyzhang1017@hotmail.com
Requires-Python: >=3.8,<4.0
Classifier: License :: OSI Approved :: MIT License
Classifier: Programming Language :: Python :: 3
Classifier: Programming Language :: Python :: 3.8
Classifier: Programming Language :: Python :: 3.9
Requires-Dist: pandas (>=1.2.2,<2.0.0)
